[
  {
    "event": "UFC Fight Night: Whittaker vs. de Ridder",
    "event_type": "Fight Night",
    "event_date": "2025-07-26",
    "event_time": "12:00",
    "fighter1": "Asu Almabayev",
    "fighter2": "Ramazan Temirov",
    "fight_order": 1,
    "card_section": "Prelim",
    "weight_class": "125",
    "scraped_at": "2025-05-22T01:04:53.937314"
  },
  {
    "event": "UFC Fight Night: Whittaker vs. de Ridder",
    "event_type": "Fight Night",
    "event_date": "2025-07-26",
    "event_time": "12:00",
    "fighter1": "Shara Magomedov",
    "fighter2": "Marc-André Barriault",
    "fight_order": 2,
    "card_section": "Main Card",
    "weight_class": "185",
    "scraped_at": "2025-05-22T01:04:53.939149"
  },
  {
    "event": "UFC Fight Night: Whittaker vs. de Ridder",
    "event_type": "Fight Night",
    "event_date": "2025-07-26",
    "event_time": "12:00",
    "fighter1": "Nikita Krylov",
    "fighter2": "Bogdan Guskov",
    "fight_order": 3,
    "card_section": "Main Card",
    "weight_class": "205",
    "scraped_at": "2025-05-22T01:04:53.941116"
  },
  {
    "event": "UFC Fight Night: Whittaker vs. de Ridder",
    "event_type": "Fight Night",
    "event_date": "2025-07-26",
    "event_time": "12:00",
    "fighter1": "Ibo Aslan",
    "fighter2": "Billy Elekana",
    "fight_order": 4,
    "card_section": "Main Card",
    "weight_class": "205",
    "scraped_at": "2025-05-22T01:04:53.943327"
  },
  {
    "event": "UFC Fight Night: Whittaker vs. de Ridder",
    "event_type": "Fight Night",
    "event_date": "2025-07-26",
    "event_time": "12:00",
    "fighter1": "Robert Whittaker",
    "fighter2": "Reinier de Ridder",
    "fight_order": 5,
    "card_section": "Main Event",
    "weight_class": "185",
    "scraped_at": "2025-05-22T01:04:53.945301"
  },
  {
    "event": "UFC Fight Night: Blanchfield vs. Barber",
    "event_type": "Fight Night",
    "event_date": "2025-05-31",
    "event_time": "18:00",
    "fighter1": "Rayanne dos Santos",
    "fighter2": "Alice Ardelean",
    "fight_order": 1,
    "card_section": "Prelim",
    "weight_class": "115",
    "scraped_at": "2025-05-22T01:04:59.939967"
  },
  {
    "event": "UFC Fight Night: Blanchfield vs. Barber",
    "event_type": "Fight Night",
    "event_date": "2025-05-31",
    "event_time": "18:00",
    "fighter1": "MarQuel Mederos",
    "fighter2": "Bolaji Oki",
    "fight_order": 2,
    "card_section": "Prelim",
    "weight_class": "155",
    "scraped_at": "2025-05-22T01:04:59.940651"
  },
  {
    "event": "UFC Fight Night: Blanchfield vs. Barber",
    "event_type": "Fight Night",
    "event_date": "2025-05-31",
    "event_time": "18:00",
    "fighter1": "Jordan Leavitt",
    "fighter2": "Kurt Holobaugh",
    "fight_order": 3,
    "card_section": "Prelim",
    "weight_class": "155",
    "scraped_at": "2025-05-22T01:04:59.941313"
  },
  {
    "event": "UFC Fight Night: Blanchfield vs. Barber",
    "event_type": "Fight Night",
    "event_date": "2025-05-31",
    "event_time": "18:00",
    "fighter1": "Oban Elliott",
    "fighter2": "Ramiz Brahimaj",
    "fight_order": 4,
    "card_section": "Prelim",
    "weight_class": "170",
    "scraped_at": "2025-05-22T01:04:59.941983"
  },
  {
    "event": "UFC Fight Night: Blanchfield vs. Barber",
    "event_type": "Fight Night",
    "event_date": "2025-05-31",
    "event_time": "18:00",
    "fighter1": "Ketlen Vieira",
    "fighter2": "Macy Chiasson",
    "fight_order": 5,
    "card_section": "Prelim",
    "weight_class": "135",
    "scraped_at": "2025-05-22T01:04:59.942654"
  },
  {
    "event": "UFC Fight Night: Blanchfield vs. Barber",
    "event_type": "Fight Night",
    "event_date": "2025-05-31",
    "event_time": "18:00",
    "fighter1": "Allan Nascimento",
    "fighter2": "Jafel Filho",
    "fight_order": 6,
    "card_section": "Prelim",
    "weight_class": "125",
    "scraped_at": "2025-05-22T01:04:59.943261"
  },
  {
    "event": "UFC Fight Night: Blanchfield vs. Barber",
    "event_type": "Fight Night",
    "event_date": "2025-05-31",
    "event_time": "18:00",
    "fighter1": "Zach Reese",
    "fighter2": "Duško Todorović",
    "fight_order": 7,
    "card_section": "Main Card",
    "weight_class": "185",
    "scraped_at": "2025-05-22T01:04:59.943926"
  },
  {
    "event": "UFC Fight Night: Blanchfield vs. Barber",
    "event_type": "Fight Night",
    "event_date": "2025-05-31",
    "event_time": "18:00",
    "fighter1": "Dustin Jacoby",
    "fighter2": "Bruno Lopes",
    "fight_order": 8,
    "card_section": "Main Card",
    "weight_class": "205",
    "scraped_at": "2025-05-22T01:04:59.944599"
  },
  {
    "event": "UFC Fight Night: Blanchfield vs. Barber",
    "event_type": "Fight Night",
    "event_date": "2025-05-31",
    "event_time": "18:00",
    "fighter1": "Seok Hyun Ko",
    "fighter2": "Billy Ray Goff",
    "fight_order": 9,
    "card_section": "Main Card",
    "weight_class": "170",
    "scraped_at": "2025-05-22T01:04:59.945270"
  },
  {
    "event": "UFC Fight Night: Blanchfield vs. Barber",
    "event_type": "Fight Night",
    "event_date": "2025-05-31",
    "event_time": "18:00",
    "fighter1": "Mateusz Gamrot",
    "fighter2": "Ľudovít Klein",
    "fight_order": 10,
    "card_section": "Co-Main",
    "weight_class": "155",
    "scraped_at": "2025-05-22T01:04:59.945929"
  },
  {
    "event": "UFC Fight Night: Blanchfield vs. Barber",
    "event_type": "Fight Night",
    "event_date": "2025-05-31",
    "event_time": "18:00",
    "fighter1": "Erin Blanchfield",
    "fighter2": "Maycee Barber",
    "fight_order": 11,
    "card_section": "Main Event",
    "weight_class": "125",
    "scraped_at": "2025-05-22T01:04:59.946589"
  },
  {
    "event": "UFC Fight Night: Usman vs. Buckley",
    "event_type": "Fight Night",
    "event_date": "2025-06-14",
    "event_time": "18:00",
    "fighter1": "Cody Durden",
    "fighter2": "Jose Ochoa",
    "fight_order": 1,
    "card_section": "Prelim",
    "weight_class": "125",
    "scraped_at": "2025-05-22T01:05:04.963641"
  },
  {
    "event": "UFC Fight Night: Usman vs. Buckley",
    "event_type": "Fight Night",
    "event_date": "2025-06-14",
    "event_time": "18:00",
    "fighter1": "Jamey-Lyn Horth",
    "fighter2": "Tereza Bledá",
    "fight_order": 2,
    "card_section": "Prelim",
    "weight_class": "125",
    "scraped_at": "2025-05-22T01:05:04.964363"
  },
  {
    "event": "UFC Fight Night: Usman vs. Buckley",
    "event_type": "Fight Night",
    "event_date": "2025-06-14",
    "event_time": "18:00",
    "fighter1": "Ricky Simón",
    "fighter2": "Charles Jourdain",
    "fight_order": 3,
    "card_section": "Main Card",
    "weight_class": "135",
    "scraped_at": "2025-05-22T01:05:04.965043"
  },
  {
    "event": "UFC Fight Night: Usman vs. Buckley",
    "event_type": "Fight Night",
    "event_date": "2025-06-14",
    "event_time": "18:00",
    "fighter1": "Cody Garbrandt",
    "fighter2": "Raoni Barcelos",
    "fight_order": 4,
    "card_section": "Main Card",
    "weight_class": "135",
    "scraped_at": "2025-05-22T01:05:04.965927"
  },
  {
    "event": "UFC Fight Night: Usman vs. Buckley",
    "event_type": "Fight Night",
    "event_date": "2025-06-14",
    "event_time": "18:00",
    "fighter1": "Michael Chiesa",
    "fighter2": "Court McGee",
    "fight_order": 5,
    "card_section": "Main Card",
    "weight_class": "170",
    "scraped_at": "2025-05-22T01:05:04.966602"
  },
  {
    "event": "UFC Fight Night: Usman vs. Buckley",
    "event_type": "Fight Night",
    "event_date": "2025-06-14",
    "event_time": "18:00",
    "fighter1": "Cody Brundage",
    "fighter2": "Mansur Abdul-Malik",
    "fight_order": 6,
    "card_section": "Main Card",
    "weight_class": "185",
    "scraped_at": "2025-05-22T01:05:04.967304"
  },
  {
    "event": "UFC Fight Night: Usman vs. Buckley",
    "event_type": "Fight Night",
    "event_date": "2025-06-14",
    "event_time": "18:00",
    "fighter1": "Edmen Shahbazyan",
    "fighter2": "Andre Petroski",
    "fight_order": 7,
    "card_section": "Main Card",
    "weight_class": "185",
    "scraped_at": "2025-05-22T01:05:04.967980"
  },
  {
    "event": "UFC Fight Night: Usman vs. Buckley",
    "event_type": "Fight Night",
    "event_date": "2025-06-14",
    "event_time": "18:00",
    "fighter1": "Alonzo Menifield",
    "fighter2": "Oumar Sy",
    "fight_order": 8,
    "card_section": "Main Card",
    "weight_class": "205",
    "scraped_at": "2025-05-22T01:05:04.968651"
  },
  {
    "event": "UFC Fight Night: Usman vs. Buckley",
    "event_type": "Fight Night",
    "event_date": "2025-06-14",
    "event_time": "18:00",
    "fighter1": "Rose Namajunas",
    "fighter2": "Miranda Maverick",
    "fight_order": 9,
    "card_section": "Co-Main",
    "weight_class": "125",
    "scraped_at": "2025-05-22T01:05:04.969308"
  },
  {
    "event": "UFC Fight Night: Usman vs. Buckley",
    "event_type": "Fight Night",
    "event_date": "2025-06-14",
    "event_time": "18:00",
    "fighter1": "Kamaru Usman",
    "fighter2": "Joaquin Buckley",
    "fight_order": 10,
    "card_section": "Main Event",
    "weight_class": "170",
    "scraped_at": "2025-05-22T01:05:04.970372"
  },
  {
    "event": "UFC Fight Night",
    "event_type": "Fight Night",
    "event_date": "2025-08-09",
    "event_time": "18:00",
    "fighter1": "Gabriella Fernandes",
    "fighter2": "Julija Stoliarenko",
    "fight_order": 1,
    "card_section": "Prelim",
    "weight_class": "125",
    "scraped_at": "2025-05-22T01:05:08.493703"
  },
  {
    "event": "UFC Fight Night",
    "event_type": "Fight Night",
    "event_date": "2025-08-09",
    "event_time": "18:00",
    "fighter1": "Julius Walker",
    "fighter2": "Raffael Cerqueira",
    "fight_order": 2,
    "card_section": "Prelim",
    "weight_class": "205",
    "scraped_at": "2025-05-22T01:05:08.494695"
  },
  {
    "event": "UFC Fight Night",
    "event_type": "Fight Night",
    "event_date": "2025-08-09",
    "event_time": "18:00",
    "fighter1": "Eryk Anders",
    "fighter2": "Christian Leroy Duncan",
    "fight_order": 3,
    "card_section": "Main Card",
    "weight_class": "185",
    "scraped_at": "2025-05-22T01:05:08.495621"
  },
  {
    "event": "UFC Fight Night",
    "event_type": "Fight Night",
    "event_date": "2025-08-09",
    "event_time": "18:00",
    "fighter1": "Roman Dolidze",
    "fighter2": "Anthony Hernandez",
    "fight_order": 4,
    "card_section": "* Rumor *",
    "weight_class": "185",
    "scraped_at": "2025-05-22T01:05:08.496995"
  },
  {
    "event": "UFC Fight Night: Hill vs. Rountree",
    "event_type": "Fight Night",
    "event_date": "2025-06-21",
    "event_time": "12:00",
    "fighter1": "Muhammad Naimov",
    "fighter2": "Bogdan Grad",
    "fight_order": 1,
    "card_section": "Prelim",
    "weight_class": "145",
    "scraped_at": "2025-05-22T01:05:13.601651"
  },
  {
    "event": "UFC Fight Night: Hill vs. Rountree",
    "event_type": "Fight Night",
    "event_date": "2025-06-21",
    "event_time": "12:00",
    "fighter1": "Nazim Sadykhov",
    "fighter2": "Nikolas Motta",
    "fight_order": 2,
    "card_section": "Prelim",
    "weight_class": "155",
    "scraped_at": "2025-05-22T01:05:13.603399"
  },
  {
    "event": "UFC Fight Night: Hill vs. Rountree",
    "event_type": "Fight Night",
    "event_date": "2025-06-21",
    "event_time": "12:00",
    "fighter1": "Darya Zheleznyakova",
    "fighter2": "Melissa Mullins",
    "fight_order": 3,
    "card_section": "Prelim",
    "weight_class": "135",
    "scraped_at": "2025-05-22T01:05:13.605782"
  },
  {
    "event": "UFC Fight Night: Hill vs. Rountree",
    "event_type": "Fight Night",
    "event_date": "2025-06-21",
    "event_time": "12:00",
    "fighter1": "Irina Alekseeva",
    "fighter2": "Klaudia Syguła",
    "fight_order": 4,
    "card_section": "Prelim",
    "weight_class": "135",
    "scraped_at": "2025-05-22T01:05:13.608003"
  },
  {
    "event": "UFC Fight Night: Hill vs. Rountree",
    "event_type": "Fight Night",
    "event_date": "2025-06-21",
    "event_time": "12:00",
    "fighter1": "Mohammed Usman",
    "fighter2": "Hamdy Abdelwahab",
    "fight_order": 5,
    "card_section": "Prelim",
    "weight_class": "265",
    "scraped_at": "2025-05-22T01:05:13.609482"
  },
  {
    "event": "UFC Fight Night: Hill vs. Rountree",
    "event_type": "Fight Night",
    "event_date": "2025-06-21",
    "event_time": "12:00",
    "fighter1": "Tagir Ulanbekov",
    "fighter2": "Azat Maksum",
    "fight_order": 6,
    "card_section": "Main Card",
    "weight_class": "125",
    "scraped_at": "2025-05-22T01:05:13.610960"
  },
  {
    "event": "UFC Fight Night: Hill vs. Rountree",
    "event_type": "Fight Night",
    "event_date": "2025-06-21",
    "event_time": "12:00",
    "fighter1": "Curtis Blaydes",
    "fighter2": "Rizvan Kuniev",
    "fight_order": 7,
    "card_section": "Main Card",
    "weight_class": "265",
    "scraped_at": "2025-05-22T01:05:13.612459"
  },
  {
    "event": "UFC Fight Night: Hill vs. Rountree",
    "event_type": "Fight Night",
    "event_date": "2025-06-21",
    "event_time": "12:00",
    "fighter1": "Ismail Naurdiev",
    "fighter2": "Jun Yong Park",
    "fight_order": 8,
    "card_section": "Main Card",
    "weight_class": "185",
    "scraped_at": "2025-05-22T01:05:13.613718"
  },
  {
    "event": "UFC Fight Night: Hill vs. Rountree",
    "event_type": "Fight Night",
    "event_date": "2025-06-21",
    "event_time": "12:00",
    "fighter1": "Rafael Fiziev",
    "fighter2": "Ignacio Bahamondes",
    "fight_order": 9,
    "card_section": "Co-Main",
    "weight_class": "155",
    "scraped_at": "2025-05-22T01:05:13.616333"
  },
  {
    "event": "UFC Fight Night: Hill vs. Rountree",
    "event_type": "Fight Night",
    "event_date": "2025-06-21",
    "event_time": "12:00",
    "fighter1": "Jamahal Hill",
    "fighter2": "Khalil Rountree Jr.",
    "fight_order": 10,
    "card_section": "Main Event",
    "weight_class": "205",
    "scraped_at": "2025-05-22T01:05:13.618345"
  },
  {
    "event": "UFC 317: Topuria vs. Oliveira",
    "event_type": "PPV",
    "event_date": "2025-06-28",
    "event_time": "18:00",
    "fighter1": "Jack Hermansson",
    "fighter2": "Gregory Rodrigues",
    "fight_order": 1,
    "card_section": "Prelim",
    "weight_class": "185",
    "scraped_at": "2025-05-22T01:05:18.060408"
  },
  {
    "event": "UFC 317: Topuria vs. Oliveira",
    "event_type": "PPV",
    "event_date": "2025-06-28",
    "event_time": "18:00",
    "fighter1": "Viviane Araujo",
    "fighter2": "Tracy Cortez",
    "fight_order": 2,
    "card_section": "Prelim",
    "weight_class": "125",
    "scraped_at": "2025-05-22T01:05:18.061109"
  },
  {
    "event": "UFC 317: Topuria vs. Oliveira",
    "event_type": "PPV",
    "event_date": "2025-06-28",
    "event_time": "18:00",
    "fighter1": "Jhonata Diniz",
    "fighter2": "Justin Tafa",
    "fight_order": 3,
    "card_section": "Prelim",
    "weight_class": "265",
    "scraped_at": "2025-05-22T01:05:18.061811"
  },
  {
    "event": "UFC 317: Topuria vs. Oliveira",
    "event_type": "PPV",
    "event_date": "2025-06-28",
    "event_time": "18:00",
    "fighter1": "Brandon Royval",
    "fighter2": "Manel Kape",
    "fight_order": 4,
    "card_section": "Prelim",
    "weight_class": "125",
    "scraped_at": "2025-05-22T01:05:18.062840"
  },
  {
    "event": "UFC 317: Topuria vs. Oliveira",
    "event_type": "PPV",
    "event_date": "2025-06-28",
    "event_time": "18:00",
    "fighter1": "Michael Johnson",
    "fighter2": "Daniel Zellhuber",
    "fight_order": 5,
    "card_section": "Prelim",
    "weight_class": "155",
    "scraped_at": "2025-05-22T01:05:18.063565"
  },
  {
    "event": "UFC 317: Topuria vs. Oliveira",
    "event_type": "PPV",
    "event_date": "2025-06-28",
    "event_time": "18:00",
    "fighter1": "Beneil Dariush",
    "fighter2": "Renato Moicano",
    "fight_order": 6,
    "card_section": "Main Card",
    "weight_class": "155",
    "scraped_at": "2025-05-22T01:05:18.064308"
  },
  {
    "event": "UFC 317: Topuria vs. Oliveira",
    "event_type": "PPV",
    "event_date": "2025-06-28",
    "event_time": "18:00",
    "fighter1": "Paulo Costa",
    "fighter2": "Roman Kopylov",
    "fight_order": 7,
    "card_section": "Main Card",
    "weight_class": "185",
    "scraped_at": "2025-05-22T01:05:18.064979"
  },
  {
    "event": "UFC 317: Topuria vs. Oliveira",
    "event_type": "PPV",
    "event_date": "2025-06-28",
    "event_time": "18:00",
    "fighter1": "Alexandre Pantoja",
    "fighter2": "Kai Kara-France",
    "fight_order": 8,
    "card_section": "Co-Main",
    "weight_class": "125",
    "scraped_at": "2025-05-22T01:05:18.065789"
  },
  {
    "event": "UFC 317: Topuria vs. Oliveira",
    "event_type": "PPV",
    "event_date": "2025-06-28",
    "event_time": "18:00",
    "fighter1": "Ilia Topuria",
    "fighter2": "Charles Oliveira",
    "fight_order": 9,
    "card_section": "Main Event",
    "weight_class": "155",
    "scraped_at": "2025-05-22T01:05:18.066539"
  },
  {
    "event": "UFC Fight Night",
    "event_type": "Fight Night",
    "event_date": "2025-08-02",
    "event_time": "18:00",
    "fighter1": "Nick Klein",
    "fighter2": "Andrey Pulyaev",
    "fight_order": 1,
    "card_section": "Prelim",
    "weight_class": "185",
    "scraped_at": "2025-05-22T01:05:22.058255"
  },
  {
    "event": "UFC Fight Night",
    "event_type": "Fight Night",
    "event_date": "2025-08-02",
    "event_time": "18:00",
    "fighter1": "Karol Rosa",
    "fighter2": "Nora Cornolle",
    "fight_order": 2,
    "card_section": "Prelim",
    "weight_class": "135",
    "scraped_at": "2025-05-22T01:05:22.058954"
  },
  {
    "event": "UFC Fight Night",
    "event_type": "Fight Night",
    "event_date": "2025-08-02",
    "event_time": "18:00",
    "fighter1": "Piera Rodriguez",
    "fighter2": "Ketlen Souza",
    "fight_order": 3,
    "card_section": "Prelim",
    "weight_class": "115",
    "scraped_at": "2025-05-22T01:05:22.059640"
  },
  {
    "event": "UFC Fight Night",
    "event_type": "Fight Night",
    "event_date": "2025-08-02",
    "event_time": "18:00",
    "fighter1": "André Lima",
    "fighter2": "Felipe Bunes",
    "fight_order": 4,
    "card_section": "Prelim",
    "weight_class": "125",
    "scraped_at": "2025-05-22T01:05:22.060319"
  },
  {
    "event": "UFC Fight Night",
    "event_type": "Fight Night",
    "event_date": "2025-08-02",
    "event_time": "18:00",
    "fighter1": "Amir Albazi",
    "fighter2": "Tatsuro Taira",
    "fight_order": 5,
    "card_section": "Main Card",
    "weight_class": "125",
    "scraped_at": "2025-05-22T01:05:22.060984"
  },
  {
    "event": "UFC 316: Dvalishvili vs. O'Malley 2",
    "event_type": "PPV",
    "event_date": "2025-06-07",
    "event_time": "18:00",
    "fighter1": "Quillan Salkilld",
    "fighter2": "Yanal Ashmouz",
    "fight_order": 1,
    "card_section": "Prelim",
    "weight_class": "155",
    "scraped_at": "2025-05-22T01:05:40.563466"
  },
  {
    "event": "UFC 316: Dvalishvili vs. O'Malley 2",
    "event_type": "PPV",
    "event_date": "2025-06-07",
    "event_time": "18:00",
    "fighter1": "Azamat Murzakanov",
    "fighter2": "Brendson Ribeiro",
    "fight_order": 2,
    "card_section": "Prelim",
    "weight_class": "205",
    "scraped_at": "2025-05-22T01:05:40.564154"
  },
  {
    "event": "UFC 316: Dvalishvili vs. O'Malley 2",
    "event_type": "PPV",
    "event_date": "2025-06-07",
    "event_time": "18:00",
    "fighter1": "Khaos Williams",
    "fighter2": "Uros Medic",
    "fight_order": 3,
    "card_section": "Prelim",
    "weight_class": "170",
    "scraped_at": "2025-05-22T01:05:40.564818"
  },
  {
    "event": "UFC 316: Dvalishvili vs. O'Malley 2",
    "event_type": "PPV",
    "event_date": "2025-06-07",
    "event_time": "18:00",
    "fighter1": "Joo Sang Yoo",
    "fighter2": "Jeka Saragih",
    "fight_order": 4,
    "card_section": "Prelim",
    "weight_class": "145",
    "scraped_at": "2025-05-22T01:05:40.565502"
  },
  {
    "event": "UFC 316: Dvalishvili vs. O'Malley 2",
    "event_type": "PPV",
    "event_date": "2025-06-07",
    "event_time": "18:00",
    "fighter1": "Serghei Spivac",
    "fighter2": "Waldo Cortes-Acosta",
    "fight_order": 5,
    "card_section": "Prelim",
    "weight_class": "265",
    "scraped_at": "2025-05-22T01:05:40.566184"
  },
  {
    "event": "UFC 316: Dvalishvili vs. O'Malley 2",
    "event_type": "PPV",
    "event_date": "2025-06-07",
    "event_time": "18:00",
    "fighter1": "Ariane Lipski da Silva",
    "fighter2": "Cong Wang",
    "fight_order": 6,
    "card_section": "Prelim",
    "weight_class": "125",
    "scraped_at": "2025-05-22T01:05:40.566881"
  },
  {
    "event": "UFC 316: Dvalishvili vs. O'Malley 2",
    "event_type": "PPV",
    "event_date": "2025-06-07",
    "event_time": "18:00",
    "fighter1": "Bruno Silva",
    "fighter2": "Joshua Van",
    "fight_order": 7,
    "card_section": "Prelim",
    "weight_class": "125",
    "scraped_at": "2025-05-22T01:05:40.567561"
  },
  {
    "event": "UFC 316: Dvalishvili vs. O'Malley 2",
    "event_type": "PPV",
    "event_date": "2025-06-07",
    "event_time": "18:00",
    "fighter1": "Mario Bautista",
    "fighter2": "Patchy Mix",
    "fight_order": 8,
    "card_section": "Main Card",
    "weight_class": "135",
    "scraped_at": "2025-05-22T01:05:40.568250"
  },
  {
    "event": "UFC 316: Dvalishvili vs. O'Malley 2",
    "event_type": "PPV",
    "event_date": "2025-06-07",
    "event_time": "18:00",
    "fighter1": "Vicente Luque",
    "fighter2": "Kevin Holland",
    "fight_order": 9,
    "card_section": "Main Card",
    "weight_class": "170",
    "scraped_at": "2025-05-22T01:05:40.568921"
  },
  {
    "event": "UFC 316: Dvalishvili vs. O'Malley 2",
    "event_type": "PPV",
    "event_date": "2025-06-07",
    "event_time": "18:00",
    "fighter1": "Kelvin Gastelum",
    "fighter2": "Joe Pyfer",
    "fight_order": 10,
    "card_section": "Main Card",
    "weight_class": "185",
    "scraped_at": "2025-05-22T01:05:40.569604"
  },
  {
    "event": "UFC 316: Dvalishvili vs. O'Malley 2",
    "event_type": "PPV",
    "event_date": "2025-06-07",
    "event_time": "18:00",
    "fighter1": "Julianna Peña",
    "fighter2": "Kayla Harrison",
    "fight_order": 11,
    "card_section": "Co-Main",
    "weight_class": "135",
    "scraped_at": "2025-05-22T01:05:40.570401"
  },
  {
    "event": "UFC 316: Dvalishvili vs. O'Malley 2",
    "event_type": "PPV",
    "event_date": "2025-06-07",
    "event_time": "18:00",
    "fighter1": "Merab Dvalishvili",
    "fighter2": "Sean O'Malley",
    "fight_order": 12,
    "card_section": "Main Event",
    "weight_class": "135",
    "scraped_at": "2025-05-22T01:05:40.571211"
  },
  {
    "event": "UFC 318: Holloway vs. Poirier 3",
    "event_type": "PPV",
    "event_date": "2025-07-19",
    "event_time": "18:00",
    "fighter1": "Jimmy Crute",
    "fighter2": "Marcin Prachnio",
    "fight_order": 1,
    "card_section": "Prelim",
    "weight_class": "205",
    "scraped_at": "2025-05-22T01:05:44.654646"
  },
  {
    "event": "UFC 318: Holloway vs. Poirier 3",
    "event_type": "PPV",
    "event_date": "2025-07-19",
    "event_time": "18:00",
    "fighter1": "Carli Judice",
    "fighter2": "Nicolle Caliari",
    "fight_order": 2,
    "card_section": "Prelim",
    "weight_class": "125",
    "scraped_at": "2025-05-22T01:05:44.655966"
  },
  {
    "event": "UFC 318: Holloway vs. Poirier 3",
    "event_type": "PPV",
    "event_date": "2025-07-19",
    "event_time": "18:00",
    "fighter1": "Kyler Phillips",
    "fighter2": "Vinicius Oliveira",
    "fight_order": 3,
    "card_section": "Prelim",
    "weight_class": "135",
    "scraped_at": "2025-05-22T01:05:44.657829"
  },
  {
    "event": "UFC 318: Holloway vs. Poirier 3",
    "event_type": "PPV",
    "event_date": "2025-07-19",
    "event_time": "18:00",
    "fighter1": "Neil Magny",
    "fighter2": "Gunnar Nelson",
    "fight_order": 4,
    "card_section": "Prelim",
    "weight_class": "170",
    "scraped_at": "2025-05-22T01:05:44.658940"
  },
  {
    "event": "UFC 318: Holloway vs. Poirier 3",
    "event_type": "PPV",
    "event_date": "2025-07-19",
    "event_time": "18:00",
    "fighter1": "Ikram Aliskerov",
    "fighter2": "Brunno Ferreira",
    "fight_order": 5,
    "card_section": "Prelim",
    "weight_class": "185",
    "scraped_at": "2025-05-22T01:05:44.661181"
  },
  {
    "event": "UFC 318: Holloway vs. Poirier 3",
    "event_type": "PPV",
    "event_date": "2025-07-19",
    "event_time": "18:00",
    "fighter1": "Amanda Ribas",
    "fighter2": "Tabatha Ricci",
    "fight_order": 6,
    "card_section": "Prelim",
    "weight_class": "115",
    "scraped_at": "2025-05-22T01:05:44.663443"
  },
  {
    "event": "UFC 318: Holloway vs. Poirier 3",
    "event_type": "PPV",
    "event_date": "2025-07-19",
    "event_time": "18:00",
    "fighter1": "Adam Fugitt",
    "fighter2": "Islam Dulatov",
    "fight_order": 7,
    "card_section": "Prelim",
    "weight_class": "170",
    "scraped_at": "2025-05-22T01:05:44.665644"
  },
  {
    "event": "UFC 318: Holloway vs. Poirier 3",
    "event_type": "PPV",
    "event_date": "2025-07-19",
    "event_time": "18:00",
    "fighter1": "Marvin Vettori",
    "fighter2": "Brendan Allen",
    "fight_order": 8,
    "card_section": "Main Card",
    "weight_class": "185",
    "scraped_at": "2025-05-22T01:05:44.667948"
  },
  {
    "event": "UFC 318: Holloway vs. Poirier 3",
    "event_type": "PPV",
    "event_date": "2025-07-19",
    "event_time": "18:00",
    "fighter1": "Max Holloway",
    "fighter2": "Dustin Poirier",
    "fight_order": 9,
    "card_section": "Main Event",
    "weight_class": "155",
    "scraped_at": "2025-05-22T01:05:44.670122"
  },
  {
    "event": "UFC 319: Du Plessis vs. Chimaev",
    "event_type": "PPV",
    "event_date": "2025-08-16",
    "event_time": "18:00",
    "fighter1": "Dricus Du Plessis",
    "fighter2": "Khamzat Chimaev",
    "fight_order": 1,
    "card_section": "Main Event",
    "weight_class": "185",
    "scraped_at": "2025-05-22T01:05:48.172152"
  },
  {
    "event": "UFC Fight Night: Lewis vs. Teixeira",
    "event_type": "Fight Night",
    "event_date": "2025-07-12",
    "event_time": "18:00",
    "fighter1": "Vitor Petrino",
    "fighter2": "Austen Lane",
    "fight_order": 1,
    "card_section": "Prelim",
    "weight_class": "265",
    "scraped_at": "2025-05-22T01:05:53.792162"
  },
  {
    "event": "UFC Fight Night: Lewis vs. Teixeira",
    "event_type": "Fight Night",
    "event_date": "2025-07-12",
    "event_time": "18:00",
    "fighter1": "Fatima Kline",
    "fighter2": "Melissa Martinez",
    "fight_order": 2,
    "card_section": "Prelim",
    "weight_class": "115",
    "scraped_at": "2025-05-22T01:05:53.792863"
  },
  {
    "event": "UFC Fight Night: Lewis vs. Teixeira",
    "event_type": "Fight Night",
    "event_date": "2025-07-12",
    "event_time": "18:00",
    "fighter1": "Lauren Murphy",
    "fighter2": "Eduarda Moura",
    "fight_order": 3,
    "card_section": "Prelim",
    "weight_class": "125",
    "scraped_at": "2025-05-22T01:05:53.793539"
  },
  {
    "event": "UFC Fight Night: Lewis vs. Teixeira",
    "event_type": "Fight Night",
    "event_date": "2025-07-12",
    "event_time": "18:00",
    "fighter1": "Calvin Kattar",
    "fighter2": "Steve Garcia",
    "fight_order": 4,
    "card_section": "Main Card",
    "weight_class": "145",
    "scraped_at": "2025-05-22T01:05:53.794205"
  },
  {
    "event": "UFC Fight Night: Lewis vs. Teixeira",
    "event_type": "Fight Night",
    "event_date": "2025-07-12",
    "event_time": "18:00",
    "fighter1": "Derrick Lewis",
    "fighter2": "Tallison Teixeira",
    "fight_order": 5,
    "card_section": "Main Event",
    "weight_class": "265",
    "scraped_at": "2025-05-22T01:05:53.794871"
  }
]